Metadata-Version: 2.1
Name: multilingual-clip
Version: 1.0.10
Summary: OpenAI CLIP text encoders for multiple languages!
Home-page: https://github.com/FreddeFrallan/Multilingual-CLIP
Author: Fredrik Carlsson
Author-email: FreddeFc@gmail.com
License: MIT
Keywords: machine learning
Platform: UNKNOWN
Classifier: Development Status :: 4 - Beta
Classifier: Intended Audience :: Developers
Classifier: Topic :: Scientific/Engineering :: Artificial Intelligence
Classifier: License :: OSI Approved :: MIT License
Classifier: Programming Language :: Python :: 3.6
Requires-Dist: transformers
